{
    "type": "FeatureCollection",
    "crs": {
        "type": "name",
        "properties": {
            "name": "urn:ogc:def:crs:OGC:1.3:CRS84"
        }
    },
    "features": [
        {
            "type": "Feature",
            "properties": {
                "OBJECTID_1": 1.0,
                "名称righ": "03020001",
                "名称": "3020001",
                "代码": "cumt10302",
                "分类号": "0302",
                "大类编": "03",
                "大类": "市容环境",
                "小类编": "02",
                "小类": "化粪池",
                "角色": "普通点",
                "n": 3787725.8465999998,
                "e": 512853.6156,
                "h": 40.2288,
                "B": "034°13′00.71393″N",
                "L": "117°08′22.15220″E",
                "H1": 40.2287,
                "基站": 1.0,
                "天线类": "CHCI80          NONE",
                "天线高": 1.8,
                "改正后": 1.9194,
                "测量方": "地形",
                "观测数": 5.0,
                "PDop": 1.40699994564,
                "HDop": 0.76399999856900003,
                "VDop": 1.1815044879900001,
                "观测卫": 25.0,
                "使用卫": 23.0,
                "星座数": 4.0,
                "解状态": "固定",
                "RMS误差": 0.0031,
                "X误差": 0.002,
                "Y误差": 0.001,
                "水平误": 0.0021,
                "垂直误": 0.004,
                "高度截": 10.0,
                "最差差": 2.0,
                "最好差": 1.0,
                "倾斜灵": 0.0,
                "倾斜限": 0.0,
                "平均倾": 0.0,
                "校正有": 0.0,
                "Tilt_Value": 0.0,
                "Tilt_X": 0.0,
                "Tilt_Y": 0.0,
                "Azimuth": 0.0,
                "测量到": "垂高",
                "开始时": "1712595712000",
                "结束时": "1712595716000",
                "数据来": "测量",
                "Latitude_d": 34.2168649806,
                "Longitude_": 117.139486722,
                "ImageUrl": null
            },
            "geometry": {
                "type": "Point",
                "coordinates": [
                    117.139486722000015,
                    34.216864981000072,
                    0.0
                ]
            }
        },
        {
            "type": "Feature",
            "properties": {
                "OBJECTID_1": 2.0,
                "名称righ": "03020002",
                "名称": "3020002",
                "代码": "cumt10302",
                "分类号": "0302",
                "大类编": "03",
                "大类": "市容环境",
                "小类编": "02",
                "小类": "化粪池",
                "角色": "普通点",
                "n": 3787724.9947000002,
                "e": 512850.237,
                "h": 40.2525,
                "B": "034°13′00.68643″N",
                "L": "117°08′22.02016″E",
                "H1": 40.2524,
                "基站": 1.0,
                "天线类": "CHCI80          NONE",
                "天线高": 1.8,
                "改正后": 1.9194,
                "测量方": "地形",
                "观测数": 5.0,
                "PDop": 1.3810000419599999,
                "HDop": 0.76300001144399998,
                "VDop": 1.1510829925499999,
                "观测卫": 24.0,
                "使用卫": 21.0,
                "星座数": 4.0,
                "解状态": "固定",
                "RMS误差": 0.0042,
                "X误差": 0.002,
                "Y误差": 0.002,
                "水平误": 0.0028,
                "垂直误": 0.0054,
                "高度截": 10.0,
                "最差差": 2.0,
                "最好差": 1.0,
                "倾斜灵": 0.0,
                "倾斜限": 0.0,
                "平均倾": 0.0,
                "校正有": 0.0,
                "Tilt_Value": 0.0,
                "Tilt_X": 0.0,
                "Tilt_Y": 0.0,
                "Azimuth": 0.0,
                "测量到": "垂高",
                "开始时": "1712595741000",
                "结束时": "1712595745000",
                "数据来": "测量",
                "Latitude_d": 34.216857341699999,
                "Longitude_": 117.139450044,
                "ImageUrl": null
            },
            "geometry": {
                "type": "Point",
                "coordinates": [
                    117.139450044,
                    34.216857342000083,
                    0.0
                ]
            }
        }
    ]
}